wordcloud_webui/__init__.py
wordcloud_webui/consts.py
wordcloud_webui/gradio_interfaces.py
wordcloud_webui/main.py
wordcloud_webui/resources/CalltoArms.txt
wordcloud_webui/resources/SourceHanSerifK-Light.otf
wordcloud_webui/resources/stopwords_cn_en.txt
wordcloud_webui/resources/mask/LuXun_color.png
wordcloud_webui/resources/mask/alice_color.png
wordcloud_webui/resources/mask/alice_mask.png
wordcloud_webui/resources/mask/parrot_mask.png
wordcloud_webui/util/__init__.py
wordcloud_webui/util/lib_jieba.py
wordcloud_webui/util/lib_wordcloud.py
wordcloud_webui-0.1.0.dist-info/LICENSE
wordcloud_webui-0.1.0.dist-info/METADATA
wordcloud_webui-0.1.0.dist-info/WHEEL
wordcloud_webui-0.1.0.dist-info/entry_points.txt
wordcloud_webui-0.1.0.dist-info/top_level.txt
wordcloud_webui-0.1.0.dist-info/RECORD
