Metadata-Version: 2.1
Name: wordcloud-webui
Version: 0.1.0
Summary: The web UI for word_cloud (text to word cloud picture converter)
Author-email: Lion A <alionsss@foxmail.com>
License: License :: OSI Approved :: Apache Software License
Project-URL: Homepage, https://github.com/AlionSSS/wordcloud-webui
Project-URL: Repository, https://github.com/AlionSSS/wordcloud-webui.git
Keywords: word-cloud,ui,webui,graph,picture,converter,text
Classifier: Development Status :: 4 - Beta
Classifier: License :: OSI Approved :: Apache Software License
Classifier: Intended Audience :: Information Technology
Classifier: Intended Audience :: Developers
Classifier: Operating System :: Microsoft :: Windows
Classifier: Operating System :: POSIX :: Linux
Classifier: Programming Language :: Python :: 3
Classifier: Programming Language :: Python :: 3.10
Classifier: Topic :: Multimedia :: Graphics
Requires-Python: >=3.6
License-File: LICENSE
Requires-Dist: gradio ==4.29
Requires-Dist: wordcloud ==1.9.3
Requires-Dist: jieba ==0.42.1
